phtml5/__init__.py
phtml5/htmlelement.py
phtml5/py.typed
phtml5/tags.py
phtml5-1.0.1.dist-info/METADATA
phtml5-1.0.1.dist-info/WHEEL
phtml5-1.0.1.dist-info/top_level.txt
phtml5-1.0.1.dist-info/RECORD
