Metadata-Version: 2.1
Name: phtml5
Version: 1.0.1
Summary: Type safe HTML DSL for Python.
Author: Thomas Poelman
License: MIT
Platform: unix
Platform: linux
Platform: osx
Platform: cygwin
Platform: win32
Classifier: Programming Language :: Python :: 3.10
Requires-Python: >=3.10
